{
  "id": "09b76556-0b53-4f4e-a849-a2dcdbcd0dd6",
  "name": "Ryan Price",
  "photo": "https://sessionize.com/image/48f3-400o400o1-DgYHA782ZUBjCNezoepmmr.jpg",
  "bio": "Ryan is an enthusiastic, polyglot software person who's worked across a ton of different domains, from operating systems &amp; infrastructure all the way up to \"data science\". He is the founder &amp; maintainer of OpenSourceCorp, a project aiming to emulate &amp; educate on typical enterprise IT environments. He loves video games, travel, food, and foreign language, whether of the software or human variety.",
  "links": [
    {
      "title": "Twitter",
      "url": "https://twitter.com/ryapric"
    },
    {
      "title": "LinkedIn",
      "url": "https://www.linkedin.com/in/ryapric/"
    },
    {
      "title": "Blog",
      "url": "https://opensourcecorp.org/blog"
    },
    {
      "title": "Company Website",
      "url": "https://opensourcecorp.org"
    }
  ]
}