{
  "id": "95cc4b00-11d7-4c8f-9a7e-e63082a3e1a2",
  "name": "Jennie Ocken",
  "photo": "https://sessionize.com/image/570b-400o400o1-fVbdEt3ybBaCSQyCj8uLcs.jpg",
  "bio": "Jennie has solved business problems with technology for over a decade and a half.  She has managed products for companies large and small with software developers, marketers, customer support, and clients from a wide variety of industries, proprietary and open source, B2B and B2B2C.  She loves talking shop about how to solve user problems and build the right thing.",
  "links": [
    {
      "title": "Twitter",
      "url": "https://twitter.com/JennieOcken"
    },
    {
      "title": "LinkedIn",
      "url": "https://www.linkedin.com/in/jennie-ocken-mba-cspo-3a867bb/"
    },
    {
      "title": "Blog",
      "url": "http://jennie.ocken.org"
    }
  ]
}